slack100bot.py
100bot-1.0.1.dist-info/DESCRIPTION.rst
100bot-1.0.1.dist-info/METADATA
100bot-1.0.1.dist-info/RECORD
100bot-1.0.1.dist-info/WHEEL
100bot-1.0.1.dist-info/entry_points.txt
100bot-1.0.1.dist-info/metadata.json
100bot-1.0.1.dist-info/top_level.txt
