Metadata-Version: 2.0
Name: 100bot
Version: 1.0.1
Summary: Spice up your Slack-life with emojis!
Home-page: https://github.com/PeppyHare/100bot
Author: Evan Bluhm
Author-email: bluhme3@gmail.com
License: UNKNOWN
Project-URL: Bug Reports, https://github.com/PeppyHare/100bot/issues
Project-URL: Source, https://github.com/PeppyHare/100bot/
Platform: UNKNOWN
Classifier: Development Status :: 4 - Beta
Classifier: Intended Audience :: Developers
Classifier: Topic :: Communications :: Chat
Classifier: License :: OSI Approved :: MIT License
Classifier: Programming Language :: Python :: 3
Requires-Dist: slackclient
Requires-Dist: requests
